frontmark/__about__.py
frontmark/__init__.py
frontmark/reader.py
frontmark/signals.py
pelican_frontmark-1.2.1.dist-info/LICENSE
pelican_frontmark-1.2.1.dist-info/METADATA
pelican_frontmark-1.2.1.dist-info/WHEEL
pelican_frontmark-1.2.1.dist-info/top_level.txt
pelican_frontmark-1.2.1.dist-info/RECORD
