Metadata-Version: 2.1
Name: pelican-frontmark
Version: 1.2.1
Summary: CommonMark/Frontmatter reader for Pelican
Home-page: https://github.com/noirbizarre/pelican-frontmark
Author: Axel Haustant
Author-email: noirbizarre+github@gmail.com
License: MIT
Keywords: pelican,markdown,frontmatter,commonmark,yaml
Platform: UNKNOWN
Classifier: Development Status :: 3 - Alpha
Classifier: Programming Language :: Python
Classifier: Environment :: Web Environment
Classifier: Operating System :: OS Independent
Classifier: Intended Audience :: Developers
Classifier: Topic :: System :: Software Distribution
Classifier: Programming Language :: Python
Classifier: Programming Language :: Python :: 3
Classifier: Programming Language :: Python :: 3.5
Classifier: Programming Language :: Python :: 3.6
Classifier: Programming Language :: Python :: 3.7
Classifier: Topic :: Software Development :: Libraries :: Python Modules
Classifier: License :: OSI Approved :: MIT License
Requires-Python: >=3.5
Requires-Dist: pelican (>=3.7.0)
Requires-Dist: pyyaml
Requires-Dist: commonmark (>=0.9.1)
Provides-Extra: qa
Requires-Dist: pytest-cov ; extra == 'qa'
Requires-Dist: flake8 ; extra == 'qa'
Provides-Extra: test
Requires-Dist: pytest ; extra == 'test'
Requires-Dist: pyquery ; extra == 'test'
